{
  "name": "backend",
  "version": "0.0.0",
  "private": true,
  "scripts": {
    "start": "NODE_ENV=prod node ./bin/www",
    "dev": "NODE_ENV=dev nodemon ./bin/www"
  },
  "author": "SSS.A.T",
  "license": "ISC",
  "dependencies": {
    "amqplib": "^0.10.9",
    "axios": "^1.7.8",
    "bcryptjs": "^2.4.3",
    "body-parser": "^1.18.3",
    "cors": "^2.8.5",
    "dotenv": "^16.0.1",
    "express": "^4.17.1",
    "express-mung": "^0.5.1",
    "form-data": "^4.0.1",
    "helmet": "^8.0.0",
    "joi": "^17.4.2",
    "jsonwebtoken": "^8.5.1",
    "moment": "^2.29.4",
    "mongoose": "^6.4.1",
    "morgan": "^1.10.0",
    "multer": "^1.4.5-lts.1",
    "nodemailer": "^6.7.8",
    "prettier": "^2.7.1",
    "uuid": "^9.0.1",
    "winston": "^3.17.0",
    "winston-daily-rotate-file": "^5.0.0"
  },
  "devDependencies": {
    "@types/amqp": "^0.2.8",
    "@types/express": "^4.17.13",
    "@types/jsonwebtoken": "^8.5.8",
    "@types/mongoose": "^5.11.97",
    "nodemon": "^2.0.12"
  }
}
